home_assistant_streamdeck_yaml.py
home_assistant_streamdeck_yaml-2026.1.0.dist-info/licenses/LICENSE
home_assistant_streamdeck_yaml-2026.1.0.dist-info/METADATA
home_assistant_streamdeck_yaml-2026.1.0.dist-info/WHEEL
home_assistant_streamdeck_yaml-2026.1.0.dist-info/entry_points.txt
home_assistant_streamdeck_yaml-2026.1.0.dist-info/top_level.txt
home_assistant_streamdeck_yaml-2026.1.0.dist-info/RECORD
