Metadata-Version: 2.4
Name: home_assistant_streamdeck_yaml
Version: 2026.1.0
Summary: Home Assistant on Stream Deck: configured via YAML (with templates) and running on Linux, MacOS, and Windows
Author-email: Bas Nijholt <bas@nijho.lt>
Project-URL: Homepage, https://github.com/basnijholt/home-assistant-streamdeck-yaml
Requires-Python: >=3.10
License-File: LICENSE
Requires-Dist: cairosvg
Requires-Dist: jinja2
Requires-Dist: lxml
Requires-Dist: pillow
Requires-Dist: pydantic<2
Requires-Dist: python-dotenv
Requires-Dist: pyyaml
Requires-Dist: requests
Requires-Dist: rich
Requires-Dist: streamdeck
Requires-Dist: websockets
Provides-Extra: test
Requires-Dist: pytest; extra == "test"
Requires-Dist: pre-commit; extra == "test"
Requires-Dist: pytest-asyncio; extra == "test"
Requires-Dist: coverage; extra == "test"
Requires-Dist: pytest-cov; extra == "test"
Provides-Extra: docs
Requires-Dist: pandas; extra == "docs"
Requires-Dist: tabulate; extra == "docs"
Requires-Dist: tqdm; extra == "docs"
Provides-Extra: colormap
Requires-Dist: matplotlib; extra == "colormap"
Dynamic: license-file
Dynamic: requires-dist
